tools_core/__init__.py
tools_core/cache_func.py
tools_core/config.py
tools_core/django.py
tools_core/email.py
tools_core/encrypt.py
tools_core/es.py
tools_core/log.py
tools_core/mq_api.py
tools_core/mq_decode.py
tools_core/multi_process.py
tools_core/multi_thread_auto.py
tools_core/mysql.py
tools_core/object_id.py
tools_core/queue.py
tools_core/queue0.py
tools_core/queue2.py
tools_core/redis.py
tools_core/send_ali_msg.py
tools_core/sqlalchemy.py
tools_core/url_uuid.py
tools_core/utils.py
tools_core/wechat.py
tools_core-0.0.1.dist-info/METADATA
tools_core-0.0.1.dist-info/WHEEL
tools_core-0.0.1.dist-info/top_level.txt
tools_core-0.0.1.dist-info/RECORD
